aliyunsdksmartag/__init__.py
aliyunsdksmartag/endpoint.py
aliyunsdksmartag/request/__init__.py
aliyunsdksmartag/request/v20180313/ActivateSmartAccessGatewayRequest.py
aliyunsdksmartag/request/v20180313/ActiveFlowLogRequest.py
aliyunsdksmartag/request/v20180313/AddACLRuleRequest.py
aliyunsdksmartag/request/v20180313/AddDnatEntryRequest.py
aliyunsdksmartag/request/v20180313/AddSnatEntryRequest.py
aliyunsdksmartag/request/v20180313/AssociateACLRequest.py
aliyunsdksmartag/request/v20180313/AssociateFlowLogRequest.py
aliyunsdksmartag/request/v20180313/AssociateQosRequest.py
aliyunsdksmartag/request/v20180313/BindSerialNumberRequest.py
aliyunsdksmartag/request/v20180313/BindSmartAccessGatewayRequest.py
aliyunsdksmartag/request/v20180313/BindVbrRequest.py
aliyunsdksmartag/request/v20180313/ClearSagCipherRequest.py
aliyunsdksmartag/request/v20180313/ClearSagRouteableAddressRequest.py
aliyunsdksmartag/request/v20180313/CreateACLRequest.py
aliyunsdksmartag/request/v20180313/CreateCloudConnectNetworkRequest.py
aliyunsdksmartag/request/v20180313/CreateEnterpriseCodeRequest.py
aliyunsdksmartag/request/v20180313/CreateFlowLogRequest.py
aliyunsdksmartag/request/v20180313/CreateHealthCheckRequest.py
aliyunsdksmartag/request/v20180313/CreateQosCarRequest.py
aliyunsdksmartag/request/v20180313/CreateQosPolicyRequest.py
aliyunsdksmartag/request/v20180313/CreateQosRequest.py
aliyunsdksmartag/request/v20180313/CreateSagExpressConnectInterfaceRequest.py
aliyunsdksmartag/request/v20180313/CreateSagStaticRouteRequest.py
aliyunsdksmartag/request/v20180313/CreateSmartAccessGatewayClientUserRequest.py
aliyunsdksmartag/request/v20180313/CreateSmartAccessGatewayRequest.py
aliyunsdksmartag/request/v20180313/CreateSmartAccessGatewaySoftwareRequest.py
aliyunsdksmartag/request/v20180313/DeactiveFlowLogRequest.py
aliyunsdksmartag/request/v20180313/DeleteACLRequest.py
aliyunsdksmartag/request/v20180313/DeleteACLRuleRequest.py
aliyunsdksmartag/request/v20180313/DeleteCloudConnectNetworkRequest.py
aliyun_python_sdk_smartag-2.0.4.dist-info/LICENSE
aliyun_python_sdk_smartag-2.0.4.dist-info/METADATA
aliyun_python_sdk_smartag-2.0.4.dist-info/WHEEL
aliyun_python_sdk_smartag-2.0.4.dist-info/top_level.txt
aliyun_python_sdk_smartag-2.0.4.dist-info/RECORD
